setup.py
Bloxflip.py.egg-info/PKG-INFO
Bloxflip.py.egg-info/SOURCES.txt
Bloxflip.py.egg-info/dependency_links.txt
Bloxflip.py.egg-info/top_level.txt
bloxflip/__init__.py
bloxflip/authorization.py
bloxflip/crash.py
bloxflip/currency.py
bloxflip/jackpot.py
bloxflip/mines.py
bloxflip/towers.py
bloxflip/websockets.py
bloxflip/utils/__init__.py
bloxflip/utils/errors.py