Metadata-Version: 2.1
Name: Bloxflip.py
Version: 2.2.24
Summary: An api wrapper for https://bloxflip.com
Author: TheOnlyIceBear
